setup.py
pyaap.egg-info/PKG-INFO
pyaap.egg-info/SOURCES.txt
pyaap.egg-info/dependency_links.txt
pyaap.egg-info/requires.txt
pyaap.egg-info/top_level.txt
yaap/__init__.py