Metadata-Version: 1.1
Name: pyaap
Version: 1.0
Summary: Yet Another Argument Parser
Home-page: https://github.com/kaniblu/pyaap
Author: Kang Min Yoo
Author-email: k@nib.lu
License: MIT
Keywords: argparse argument options
Platform: UNKNOWN
Classifier: Development Status :: 5 - Production/Stable
Classifier: Intended Audience :: Developers
Classifier: Programming Language :: Python :: 3
